gpyreg/__init__.py
gpyreg/covariance_functions.py
gpyreg/f_min_fill.py
gpyreg/formatting.py
gpyreg/gaussian_process.py
gpyreg/isotropic_covariance_functions.py
gpyreg/mean_functions.py
gpyreg/noise_functions.py
gpyreg/slice_sample.py
gpyreg/examples/example_1.py
gpyreg/examples/example_2.py
gpyreg/testing/__init__.py
gpyreg/testing/test_covariance_functions.py
gpyreg/testing/test_gaussian_process.py
gpyreg/testing/test_gaussian_process_isotropic.py
gpyreg/testing/test_isotropic_covariance_functions.py
gpyreg/testing/test_mean_functions.py
gpyreg/testing/test_noise_functions.py
gpyreg/testing/test_slice_sample.py
gpyreg/testing/test_smoothbox.py
gpyreg/testing/test_smoothbox_student_t.py
GPyReg-1.0.2.dist-info/LICENSE
GPyReg-1.0.2.dist-info/METADATA
GPyReg-1.0.2.dist-info/WHEEL
GPyReg-1.0.2.dist-info/top_level.txt
GPyReg-1.0.2.dist-info/RECORD
