Metadata-Version: 2.1
Name: GPyReg
Version: 1.0.2
Summary: Lightweight package for Gaussian process regression.
License: BSD 3-Clause License
Requires-Python: >=3.9
License-File: LICENSE
Requires-Dist: matplotlib (>=3.5.1)
Requires-Dist: numpy (>=1.22.1)
Requires-Dist: pytest (>=6.2.5)
Requires-Dist: pytest-rerunfailures (>=10.2)
Requires-Dist: scipy (>=1.7.3)
Provides-Extra: dev
Requires-Dist: sphinx (>=4.3.2) ; extra == 'dev'
Requires-Dist: sphinx-book-theme (>=0.2.0) ; extra == 'dev'
Requires-Dist: build (>=0.9.0) ; extra == 'dev'
Requires-Dist: numpydoc (>=1.2.1) ; extra == 'dev'
